LICENSE
MANIFEST.in
README.md
pyproject.toml
setup.py
darmonpoints/__init__.py
darmonpoints/arithgroup.py
darmonpoints/arithgroup_element.py
darmonpoints/arithgroup_generic.py
darmonpoints/arithgroup_nscartan.py
darmonpoints/bianchi_lseries.py
darmonpoints/cohomology_abstract.py
darmonpoints/cohomology_arithmetic.py
darmonpoints/darmonpoints.py
darmonpoints/darmonvonk.py
darmonpoints/divisors.py
darmonpoints/findcurve.py
darmonpoints/homology.py
darmonpoints/homology_abstract.py
darmonpoints/integrals.py
darmonpoints/limits.py
darmonpoints/meromorphic.py
darmonpoints/meromorphic_debug.py
darmonpoints/meromorphic_list.py
darmonpoints/meromorphic_ps.py
darmonpoints/meromorphic_ps_dlog.py
darmonpoints/meromorphic_ps_log.py
darmonpoints/mixed_extension.c
darmonpoints/mixed_extension.pyx
darmonpoints/my_p1list_nf.py
darmonpoints/ocbianchi.py
darmonpoints/ocmodule.py
darmonpoints/padicperiods.py
darmonpoints/plectic.py
darmonpoints/rationalfunctions.py
darmonpoints/representations.py
darmonpoints/sarithgroup.py
darmonpoints/schottky.py
darmonpoints/sparse.c
darmonpoints/sparse.pyx
darmonpoints/theta.py
darmonpoints/util.py
darmonpoints.egg-info/PKG-INFO
darmonpoints.egg-info/SOURCES.txt
darmonpoints.egg-info/dependency_links.txt
darmonpoints.egg-info/top_level.txt
darmonpoints/Fdoms/fdom.gp
darmonpoints/Fdoms/libfdom.so
darmonpoints/KleinianGroups-1.0/COPYING
darmonpoints/KleinianGroups-1.0/README
darmonpoints/KleinianGroups-1.0/aux.m
darmonpoints/KleinianGroups-1.0/aux.sig
darmonpoints/KleinianGroups-1.0/bianchi.m
darmonpoints/KleinianGroups-1.0/bianchi.sig
darmonpoints/KleinianGroups-1.0/changelog
darmonpoints/KleinianGroups-1.0/example.m
darmonpoints/KleinianGroups-1.0/kleinian.m
darmonpoints/KleinianGroups-1.0/kleinian.sig
darmonpoints/KleinianGroups-1.0/klngpspec
darmonpoints/KleinianGroups-1.0/drawing/maple.m
darmonpoints/KleinianGroups-1.0/drawing/maple.sig
darmonpoints/KleinianGroups-1.0/fundamentaldomains/enumeration.m
darmonpoints/KleinianGroups-1.0/fundamentaldomains/enumeration.sig
darmonpoints/KleinianGroups-1.0/fundamentaldomains/normalizedbasis.m
