Metadata-Version: 2.4
Name: darmonpoints
Version: 8.0.3
Summary: Compute non-archimedean Darmon points
Classifier: License :: OSI Approved :: GNU General Public License v3 or later (GPLv3+)
Requires-Python: >=3.9
License-File: LICENSE
Dynamic: license-file
